MANIFEST.in
README.rst
setup.cfg
setup.py
daquiri/__init__.py
daquiri/actor.py
daquiri/collections.py
daquiri/config.py
daquiri/core.py
daquiri/data.py
daquiri/experiment.py
daquiri/globals.py
daquiri/mock.py
daquiri/notifications.py
daquiri/panel.py
daquiri/scan.py
daquiri/ui.py
daquiri/utils.py
daquiri/version.py
daquiri/widgets.py
daquiri.egg-info/PKG-INFO
daquiri.egg-info/SOURCES.txt
daquiri.egg-info/dependency_links.txt
daquiri.egg-info/requires.txt
daquiri.egg-info/top_level.txt
daquiri/examples/__init__.py
daquiri/examples/minimal_app.py
daquiri/examples/plot_data.py
daquiri/examples/scanning_experiment.py
daquiri/examples/scanning_experiment_revisited.py
daquiri/examples/simple_actors.py
daquiri/examples/ui_panels.py
daquiri/examples/wrapping_instruments.py
daquiri/instrument/__init__.py
daquiri/instrument/axis.py
daquiri/instrument/front_panel.py
daquiri/instrument/ivi_front_panel.py
daquiri/instrument/resource_manager.py
daquiri/instrument/spec.py
daquiri/instrument/utils.py
daquiri/instrument/identify/__init__.py
daquiri/instrument/identify/lakeshore.py
daquiri/instrument/identify/newport.py
daquiri/instrument/identify/srs.py
daquiri/panels/__init__.py
daquiri/panels/basic_instrument_panel.py
daquiri/panels/experiment_panel.py
daquiri/panels/instrument_manager.py
daquiri/panels/log_panels.py
daquiri/resources/default_config.json
docs/Makefile
docs/source/CHANGELOG.rst
docs/source/README.rst
docs/source/conf.py
docs/source/index.rst
docs/source/modules/index.rst